MCP2221/MCP2221.py
MCP2221/__init__.py
mcp2221-1.1.0.dist-info/LICENSE
mcp2221-1.1.0.dist-info/METADATA
mcp2221-1.1.0.dist-info/WHEEL
mcp2221-1.1.0.dist-info/top_level.txt
mcp2221-1.1.0.dist-info/RECORD
