Metadata-Version: 2.1
Name: mcp2221
Version: 1.1.0
Summary: Python driver for MCP2221/A
Home-page: https://github.com/pilotak/python-mcp2221
Author: Pavel Slama
Author-email: info@pavelslama.cz
Project-URL: Bug Tracker, https://github.com/pilotak/python-mcp2221/issues
Keywords: MCP2221,MCP2221A,GPIO,ADC,DAC
Classifier: Development Status :: 5 - Production/Stable
Classifier: Programming Language :: Python :: 3
Classifier: License :: OSI Approved :: MIT License
Classifier: Operating System :: OS Independent
Classifier: Intended Audience :: Developers
Classifier: Topic :: Communications
Classifier: Topic :: System :: Hardware :: Hardware Drivers
Classifier: Topic :: System :: Hardware :: Universal Serial Bus (USB)
Requires-Python: >=3.7
License-File: LICENSE
Requires-Dist: hidapi
